README.rst
setup.py
dnacol/__init__.py
dnacol/dnacol.py
dnacol/version.py
dnacol.egg-info/PKG-INFO
dnacol.egg-info/SOURCES.txt
dnacol.egg-info/dependency_links.txt
dnacol.egg-info/entry_points.txt
dnacol.egg-info/requires.txt
dnacol.egg-info/top_level.txt