Metadata-Version: 1.1
Name: dnacol
Version: 0.4
Summary: Display FASTA/FASTQ/SAM/VCF files with colored DNA/RNA bases and quality scores (`dnacol`) or a protein sequence with colored amino acid codes (`pcol`) in the terminal
Home-page: https://github.com/koelling/dnacol/
Author: Nils Koelling
Author-email: git@nk.gl
License: MIT
Download-URL: https://github.com/koelling/dnacol/archive/v0.4.tar.gz
Keywords: dnacol rnacol pcol rna dna protein amino acid quality phred color colour bases console terminal stdout
Platform: any
Classifier: Development Status :: 4 - Beta
Classifier: License :: OSI Approved :: MIT License
Classifier: Operating System :: MacOS
Classifier: Operating System :: Unix
Classifier: Programming Language :: Python :: 2.7
Classifier: Programming Language :: Python :: 3
